llm_limiters/__init__.py
llm_limiters/audio.py
llm_limiters/constants.py
llm_limiters/core.py
llm_limiters/image.py
llm_limiters/live.py
llm_limiters-0.1.9.dist-info/licenses/LICENSE
llm_limiters-0.1.9.dist-info/METADATA
llm_limiters-0.1.9.dist-info/WHEEL
llm_limiters-0.1.9.dist-info/top_level.txt
llm_limiters-0.1.9.dist-info/RECORD
