Metadata-Version: 2.4
Name: llm-limiters
Version: 0.1.9
Summary: A thread-safe and async rate limiter for Gemini and OpenAI models.
Author-email: Nagomi Jayamani <nagomijayamani@gmail.com>
License: MIT License
Project-URL: Homepage, https://github.com/Jayam-Nagomi/llm-limiters
Classifier: Programming Language :: Python :: 3
Classifier: License :: OSI Approved :: MIT License
Classifier: Operating System :: OS Independent
Requires-Python: >=3.7
License-File: LICENSE
Dynamic: license-file
